doom3_bfg_profile/__init__.py
doom3_bfg_profile/profile.py
doom3_bfg_profile-1.0.0.dist-info/METADATA
doom3_bfg_profile-1.0.0.dist-info/WHEEL
doom3_bfg_profile-1.0.0.dist-info/licenses/LICENSE
doom3_bfg_profile-1.0.0.dist-info/RECORD
