Metadata-Version: 2.4
Name: doom3_bfg_profile
Version: 1.0.0
Summary: A package for editing DOOM 3 BFG Edition profile.bin
Project-URL: Homepage, https://github.com/andshrew/DOOM3-BFG-Profile
Project-URL: Repository, https://github.com/andshrew/DOOM3-BFG-Profile.git
Project-URL: GitHub, https://github.com/andshrew/DOOM3-BFG-Profile
Project-URL: Issues, https://github.com/andshrew/DOOM3-BFG-Profile/issues
Project-URL: Changelog, https://github.com/andshrew/DOOM3-BFG-Profile/releases
Author-email: andshrew <7409326+andshrew@users.noreply.github.com>
License: MIT
License-File: LICENSE
Classifier: License :: OSI Approved :: MIT License
Classifier: Operating System :: OS Independent
Classifier: Programming Language :: Python :: 3
Requires-Python: >=3.8
Provides-Extra: test
Requires-Dist: pytest-cov>=4.0; extra == 'test'
Requires-Dist: pytest>=7.0; extra == 'test'
